./.env
./PKG-INFO
./README.md
./mcp_config.example.json
./mcp_server_google_scholar.py
./pyproject.toml
./requirements.txt
./.idea/.gitignore
./.idea/google_scholar.iml
./.idea/misc.xml
./.idea/modules.xml
./.idea/workspace.xml
./.idea/inspectionProfiles/profiles_settings.xml
mcp_server_google_scholar-0.1.1.dist-info/METADATA
mcp_server_google_scholar-0.1.1.dist-info/WHEEL
mcp_server_google_scholar-0.1.1.dist-info/entry_points.txt
mcp_server_google_scholar-0.1.1.dist-info/RECORD
