Metadata-Version: 2.4
Name: mcp-server-google-scholar
Version: 0.1.1
Summary: MCP Server for Google Scholar via SerpApi
Author-email: Your Name <your.email@example.com>
License-Expression: MIT
Requires-Python: >=3.10
Requires-Dist: google-search-results
Requires-Dist: mcp
Requires-Dist: python-dotenv
